Workbook

Sheet Raw Data
A1: Excel Mini Task – Sales Analysis | O1: Product Master
A2: Complete the yellow columns using Excel formulas. Keep the original data unchanged.
O3: Product Code | P3: Product | Q3: Category | R3: Unit Price
A4: Task 1 | B4: Use XLOOKUP/VLOOKUP to return Product, Category and Unit Price from the Product Master table. | O4: P101 | P4: Laptop | Q4: Technology | R4: 850
A5: Task 2 | B5: Calculate Revenue, Profit, Profit Margin and Performance (High Profit if Profit >= 300). | O5: P102 | P5: Monitor | Q5: Technology | R5: 220
A6: Task 3 | B6: Go to the Analysis sheet and complete the KPIs and Region Summary, then review the Dashboard. | O6: P103 | P6: Chair | Q6: Furniture | R6: 140
O7: P104 | P7: Desk | Q7: Furniture | R7: 300
O8: P105 | P8: Phone | Q8: Technology | R8: 600
A9: Order ID | B9: Date | C9: Region | D9: Product Code | E9: Qty | F9: Cost | G9: Product | H9: Category | I9: Unit Price | J9: Revenue | K9: Profit | L9: Profit Margin | M9: Performance
A10: S-1000 | B10: 46027 | C10: North | D10: P105 | E10: 5 | F10: 2289.58 | G10: =_xlfn.XLOOKUP(D10,$O$4:$O$8,$P$4:$P$8) -> Phone | H10: =_xlfn.XLOOKUP(D10,$O$4:$O$8,$Q$4:$Q$8) -> Technology | I10: =_xlfn.XLOOKUP(D10,$O$4:$O$8,$R$4:$R$8) -> 600 | J10: =I10*E10 -> 3000 | K10: =J10-F10 -> 710.42 | L10: =K10/J10 -> 0.23680667 | M10: =IF(K10>=300,"High Profit","") -> High Profit
A11: S-1001 | B11: 46031 | C11: North | D11: P104 | E11: 4 | F11: 891.33 | G11: =_xlfn.XLOOKUP(D11,$O$4:$O$8,$P$4:$P$8) -> Desk | H11: =_xlfn.XLOOKUP(D11,$O$4:$O$8,$Q$4:$Q$8) -> Furniture | I11: =_xlfn.XLOOKUP(D11,$O$4:$O$8,$R$4:$R$8) -> 300 | J11: =I11*E11 -> 1200 | K11: =J11-F11 -> 308.67 | L11: =K11/J11 -> 0.257225 | M11: =IF(K11>=300,"High Profit","") -> High Profit
A12: S-1002 | B12: 46035 | C12: North | D12: P103 | E12: 8 | F12: 885.98 | G12: =_xlfn.XLOOKUP(D12,$O$4:$O$8,$P$4:$P$8) -> Chair | H12: =_xlfn.XLOOKUP(D12,$O$4:$O$8,$Q$4:$Q$8) -> Furniture | I12: =_xlfn.XLOOKUP(D12,$O$4:$O$8,$R$4:$R$8) -> 140 | J12: =I12*E12 -> 1120 | K12: =J12-F12 -> 234.02 | L12: =K12/J12 -> 0.20894643 | M12: =IF(K12>=300,"High Profit","")
A13: S-1003 | B13: 46039 | C13: West | D13: P105 | E13: 4 | F13: 1446.92 | G13: =_xlfn.XLOOKUP(D13,$O$4:$O$8,$P$4:$P$8) -> Phone | H13: =_xlfn.XLOOKUP(D13,$O$4:$O$8,$Q$4:$Q$8) -> Technology | I13: =_xlfn.XLOOKUP(D13,$O$4:$O$8,$R$4:$R$8) -> 600 | J13: =I13*E13 -> 2400 | K13: =J13-F13 -> 953.08 | L13: =K13/J13 -> 0.39711667 | M13: =IF(K13>=300,"High Profit","") -> High Profit
A14: S-1004 | B14: 46043 | C14: West | D14: P103 | E14: 3 | F14: 336.67 | G14: =_xlfn.XLOOKUP(D14,$O$4:$O$8,$P$4:$P$8) -> Chair | H14: =_xlfn.XLOOKUP(D14,$O$4:$O$8,$Q$4:$Q$8) -> Furniture | I14: =_xlfn.XLOOKUP(D14,$O$4:$O$8,$R$4:$R$8) -> 140 | J14: =I14*E14 -> 420 | K14: =J14-F14 -> 83.33 | L14: =K14/J14 -> 0.19840476 | M14: =IF(K14>=300,"High Profit","")
A15: S-1005 | B15: 46042 | C15: West | D15: P102 | E15: 2 | F15: 277.43 | G15: =_xlfn.XLOOKUP(D15,$O$4:$O$8,$P$4:$P$8) -> Monitor | H15: =_xlfn.XLOOKUP(D15,$O$4:$O$8,$Q$4:$Q$8) -> Technology | I15: =_xlfn.XLOOKUP(D15,$O$4:$O$8,$R$4:$R$8) -> 220 | J15: =I15*E15 -> 440 | K15: =J15-F15 -> 162.57 | L15: =K15/J15 -> 0.36947727 | M15: =IF(K15>=300,"High Profit","")
A16: S-1006 | B16: 46046 | C16: South | D16: P102 | E16: 3 | F16: 396.26 | G16: =_xlfn.XLOOKUP(D16,$O$4:$O$8,$P$4:$P$8) -> Monitor | H16: =_xlfn.XLOOKUP(D16,$O$4:$O$8,$Q$4:$Q$8) -> Technology | I16: =_xlfn.XLOOKUP(D16,$O$4:$O$8,$R$4:$R$8) -> 220 | J16: =I16*E16 -> 660 | K16: =J16-F16 -> 263.74 | L16: =K16/J16 -> 0.39960606 | M16: =IF(K16>=300,"High Profit","")
A17: S-1007 | B17: 46050 | C17: East | D17: P102 | E17: 3 | F17: 522.67 | G17: =_xlfn.XLOOKUP(D17,$O$4:$O$8,$P$4:$P$8) -> Monitor | H17: =_xlfn.XLOOKUP(D17,$O$4:$O$8,$Q$4:$Q$8) -> Technology | I17: =_xlfn.XLOOKUP(D17,$O$4:$O$8,$R$4:$R$8) -> 220 | J17: =I17*E17 -> 660 | K17: =J17-F17 -> 137.33 | L17: =K17/J17 -> 0.20807576 | M17: =IF(K17>=300,"High Profit","")
A18: S-1008 | B18: 46054 | C18: South | D18: P102 | E18: 9 | F18: 1569.64 | G18: =_xlfn.XLOOKUP(D18,$O$4:$O$8,$P$4:$P$8) -> Monitor | H18: =_xlfn.XLOOKUP(D18,$O$4:$O$8,$Q$4:$Q$8) -> Technology | I18: =_xlfn.XLOOKUP(D18,$O$4:$O$8,$R$4:$R$8) -> 220 | J18: =I18*E18 -> 1980 | K18: =J18-F18 -> 410.36 | L18: =K18/J18 -> 0.20725253 | M18: =IF(K18>=300,"High Profit","") -> High Profit
A19: S-1009 | B19: 46058 | C19: East | D19: P102 | E19: 4 | F19: 715.13 | G19: =_xlfn.XLOOKUP(D19,$O$4:$O$8,$P$4:$P$8) -> Monitor | H19: =_xlfn.XLOOKUP(D19,$O$4:$O$8,$Q$4:$Q$8) -> Technology | I19: =_xlfn.XLOOKUP(D19,$O$4:$O$8,$R$4:$R$8) -> 220 | J19: =I19*E19 -> 880 | K19: =J19-F19 -> 164.87 | L19: =K19/J19 -> 0.18735227 | M19: =IF(K19>=300,"High Profit","")
A20: S-1010 | B20: 46057 | C20: East | D20: P101 | E20: 6 | F20: 3525.53 | G20: =_xlfn.XLOOKUP(D20,$O$4:$O$8,$P$4:$P$8) -> Laptop | H20: =_xlfn.XLOOKUP(D20,$O$4:$O$8,$Q$4:$Q$8) -> Technology | I20: =_xlfn.XLOOKUP(D20,$O$4:$O$8,$R$4:$R$8) -> 850 | J20: =I20*E20 -> 5100 | K20: =J20-F20 -> 1574.47 | L20: =K20/J20 -> 0.30871961 | M20: =IF(K20>=300,"High Profit","") -> High Profit
A21: S-1011 | B21: 46061 | C21: North | D21: P101 | E21: 6 | F21: 3398.12 | G21: =_xlfn.XLOOKUP(D21,$O$4:$O$8,$P$4:$P$8) -> Laptop | H21: =_xlfn.XLOOKUP(D21,$O$4:$O$8,$Q$4:$Q$8) -> Technology | I21: =_xlfn.XLOOKUP(D21,$O$4:$O$8,$R$4:$R$8) -> 850 | J21: =I21*E21 -> 5100 | K21: =J21-F21 -> 1701.88 | L21: =K21/J21 -> 0.33370196 | M21: =IF(K21>=300,"High Profit","") -> High Profit
... A39: S-1029 | B39: 46118 | C39: South | D39: P104 | E39: 2 | F39: 382.28 | G39: =_xlfn.XLOOKUP(D39,$O$4:$O$8,$P$4:$P$8) -> Desk | H39: =_xlfn.XLOOKUP(D39,$O$4:$O$8,$Q$4:$Q$8) -> Furniture | I39: =_xlfn.XLOOKUP(D39,$O$4:$O$8,$R$4:$R$8) -> 300 | J39: =I39*E39 -> 600 | K39: =J39-F39 -> 217.72 | L39: =K39/J39 -> 0.36286667 | M39: =IF(K39>=300,"High Profit","")

Sheet Analysis
A1: Analysis – Complete the Yellow Cells
A2: Use formulas only. Do not type the answers manually.
A4: KPI / Question | B4: Your Formula / Result | D4: Region | E4: Revenue | F4: Profit
A5: Total Revenue | B5: =SUM('Raw Data'!J10:'Raw Data'!J39) -> 56290 | D5: North | E5: =SUMIF('Raw Data'!C10:'Raw Data'!C39,"North",'Raw Data'!J10:'Raw Data'!J39) -> 16960 | F5: =SUMIF('Raw Data'!C10:'Raw Data'!C39,"North",'Raw Data'!K10:'Raw Data'!K39) -> 4466.28
A6: Total Profit | B6: =SUM('Raw Data'!K10:'Raw Data'!K39) -> 15259.46 | D6: South | E6: =SUMIF('Raw Data'!C10:'Raw Data'!C39,"South",'Raw Data'!J10:'Raw Data'!J39) -> 12800 | F6: =SUMIF('Raw Data'!C10:'Raw Data'!C39,"South",'Raw Data'!K10:'Raw Data'!K39) -> 3126.24
A7: Average Revenue per Order | B7: =AVERAGE('Raw Data'!J10:'Raw Data'!J39) -> 1876.3333 | D7: East | E7: =SUMIF('Raw Data'!C10:'Raw Data'!C39,"East",'Raw Data'!J10:'Raw Data'!J39) -> 19670 | F7: =SUMIF('Raw Data'!C10:'Raw Data'!C39,"East",'Raw Data'!K10:'Raw Data'!K39) -> 5682.39
A8: Number of Orders | B8: =COUNTA('Raw Data'!A10:'Raw Data'!A39) -> 30 | D8: West | E8: =SUMIF('Raw Data'!C10:'Raw Data'!C39,"West",'Raw Data'!J10:'Raw Data'!J39) -> 6860 | F8: =SUMIF('Raw Data'!C10:'Raw Data'!C39,"West",'Raw Data'!K10:'Raw Data'!K39) -> 1984.55
A9: Technology Revenue | B9: =SUMIF('Raw Data'!H10:'Raw Data'!H39,"Technology",'Raw Data'!J10:'Raw Data'!J39) -> 41250 | D9: Grand Total | E9: =SUM(E5:E8) -> 56290 | F9: =SUM(F5:F8) -> 15259.46
A10: Furniture Revenue | B10: =SUMIF('Raw Data'!H10:'Raw Data'!H39,"Furniture",'Raw Data'!J10:'Raw Data'!J39) -> 15040
A11: East Region Orders | B11: =COUNTIF('Raw Data'!C10:'Raw Data'!C39,"East") -> 10
A14: Required Functions / Skills
A15: 1 | B15: Lookup | C15: Fill Product, Category and Unit Price in Raw Data. | D15: Hint: XLOOKUP or VLOOKUP
A16: 2 | B16: Revenue | C16: Qty × Unit Price. | D16: Use cell references
A17: 3 | B17: Profit | C17: Revenue − Cost. | D17: Use cell references
A18: 4 | B18: Profit Margin | C18: Profit ÷ Revenue. | D18: Format as %
A19: 5 | B19: Performance | C19: IF Profit >= 300 → "High Profit", else "Low Profit". | D19: Use IF
A20: 6 | B20: KPIs | C20: Use SUM, AVERAGE, COUNTA/COUNT, SUMIF and COUNTIF. | D20: Complete B5:B11
A21: 7 | B21: Region Summary | C21: Calculate Revenue and Profit for each region. | D21: Use SUMIF
A24: Business Questions
A25: Write your answer in simple words:
A26: 1. Which region generated the highest revenue? | B26: East generated the highest revenue
A27: 2. Which category generated more revenue? | B27: Technology generated more revenue
A28: 3. Mention one product that appears to perform well. | B28: Phone appears to perform well

Sheet Dashboard
A1: Mini Sales Dashboard
A3: This page will update as you complete the Analysis sheet.
A5: Total Revenue | D5: Total Profit | G5: Avg Revenue / Order | J5: Order Count
A6: =Analysis!B5 -> 56290 | D6: =Analysis!B6 -> 15259.46 | G6: =Analysis!B7 -> 1876.3333 | J6: =Analysis!B8 -> 30
A11: Region | B11: Revenue | C11: Profit
A12: North | B12: =Analysis!E5 -> 16960 | C12: =Analysis!F5 -> 4466.28
A13: South | B13: =Analysis!E6 -> 12800 | C13: =Analysis!F6 -> 3126.24
A14: East | B14: =Analysis!E7 -> 19670 | C14: =Analysis!F7 -> 5682.39
A15: West | B15: =Analysis!E8 -> 6860 | C15: =Analysis!F8 -> 1984.55
A16: Grand Total | B16: =Analysis!E9 -> 56290 | C16: =Analysis!F9 -> 15259.46
A19: Your 3 Insights
A20: 1. East generated the highest revenue among all regions
A22: 2. Technology generated more revenue than Furniture
A24: 3. East had the highest profit among all regions
